nonsequitur/__init__.py
nonsequitur-0.0.7.dist-info/METADATA
nonsequitur-0.0.7.dist-info/WHEEL
nonsequitur-0.0.7.dist-info/top_level.txt
nonsequitur-0.0.7.dist-info/zip-safe
nonsequitur-0.0.7.dist-info/RECORD
