Metadata-Version: 2.1
Name: nonsequitur
Version: 0.0.7
Summary: non sequitur jokes generator
Home-page: https://github.com/montoyamoraga/nonsequiturpy
Author: aarón montoya-moraga
Author-email: montoyamoraga@gmail.com
License: Apache License 2.0
Keywords: nonsequitur
Platform: UNKNOWN
Classifier: Programming Language :: Python :: 3
Classifier: Natural Language :: English
Classifier: Topic :: Artistic Software
Requires-Python: >=3.0, <4
Requires-Dist: pycorpora
Requires-Dist: tracery
